bacchilu_aios3/__init__.py
bacchilu_aios3/py.typed
bacchilu_aios3-0.1.0.dist-info/METADATA
bacchilu_aios3-0.1.0.dist-info/WHEEL
bacchilu_aios3-0.1.0.dist-info/RECORD
